a_pandas_ex_closest_color/LICENSE
a_pandas_ex_closest_color/README.MD
a_pandas_ex_closest_color/__init__.py
a_pandas_ex_closest_color/requirements.txt
a_pandas_ex_closest_color/thirdparty.json
a_pandas_ex_closest_color-0.10.dist-info/LICENSE.rst
a_pandas_ex_closest_color-0.10.dist-info/METADATA
a_pandas_ex_closest_color-0.10.dist-info/WHEEL
a_pandas_ex_closest_color-0.10.dist-info/top_level.txt
a_pandas_ex_closest_color-0.10.dist-info/RECORD
